{
	"$schema": "https://schemas.wp.org/trunk/theme.json",
	"version": 2,
	"title": "Fathom",
	"settings": {
		"color": {
			"palette": [
				{
					"color": "#ff5252",
					"name": "Base",
					"slug": "base"
				},
				{
					"color": "#252525",
					"name": "Contrast",
					"slug": "contrast"
				},
				{
					"color": "#ffffff",
					"name": "Primary",
					"slug": "primary"
				},
				{
					"color": "#ff2d34",
					"name": "Secondary",
					"slug": "secondary"
				},
				{
					"color": "#ff7e7e",
					"name": "Tertiary",
					"slug": "tertiary"
				}
			]
		}
	},
	"styles": {
		"typography": {
			"fontFamily": "var(--wp--preset--font-family--montagu-slab)"
		}
	}
}
